Workbook
Name Tracker_Cost: #REF!
Name Gateway_Cost: #REF!

Sheet Inputs
A1: Space-Powered Sports: Financial Model Inputs
C5: Year 1 | D5: Year 2 | E5: Year 3 | F5: Year 4 | G5: Year 5
A6: VOLUMES
A7: Units Sold (Trackers) | C7: 600 | D7: 1500 | E7: 4000 | F7: 15000 | G7: 50000
A8: Subscription Users (Avg Year) | C8: =C7*1.2 -> 720 | D8: =D7*1.2 -> 1800 | E8: =E7*1.2 -> 4800 | F8: =F7*1.2 -> 18000 | G8: =G7*1.2 -> 60000
A9: Months Billed per Year | C9: 10 | D9: 10.5 | E9: 11 | F9: 11.5 | G9: 11.5
A11: PRICING
A12: Tracker Price (retail) | C12: 199 | D12: 199 | E12: 199 | F12: 199 | G12: 199
A13: Subscription Price (per user / month) | C13: 20 | D13: 20 | E13: 20 | F13: 20 | G13: 20
A14: SERVICE COSTS
A15: Satellite Cost (per user / month) | C15: 6 | D15: 6 | E15: 6 | F15: 6 | G15: 6
A17: OPERATING EXPENSES (ANNUAL)
A18: Salaries & Contractors | C18: 160000 | D18: 168000 | E18: 184000 | F18: 216000 | G18: 256000
A19: Marketing | C19: 30000 | D19: 31500 | E19: 34500 | F19: 40500 | G19: 48000
A20: Overheads (rent, tools, travel) | C20: 5000 | D20: 5250 | E20: 5750 | F20: 6750 | G20: 8000
A21: Cloud Infra (fixed) | C21: 6000 | D21: 6300 | E21: 6900 | F21: 8100 | G21: 9600
A22: Other Expenses | C22: 4000 | D22: 4200 | E22: 4600 | F22: 5400 | G22: 6400

Sheet BOM
A1: Bill of Materials
A3: TRACKER DEVICE
A4: Part | B4: Unit Cost (€)
A5: MCU + GNSS module | B5: 12
A6: HR + SpO₂ sensor | B6: 3
A7: IMU (accel/gyro) | B7: 2
A8: LoRa/BLE radio | B8: 4
A9: Barometer / UV / Temp | B9: 3
A10: PCB + components misc | B10: 10
A11: Battery | B11: 8
A12: Enclosure (IP-rated) | B12: 4
A13: Assembly & test | B13: 5
A14: Satellite Modem | B14: 130
B15: =SUM(B4:B14) -> 181

Sheet Model
A1: 5-Year Financial Model (formulas reference Inputs & BOM)
A3: Metric | B3: Year 1 | C3: Year 2 | D3: Year 3 | E3: Year 4 | F3: Year 5
A4: Units Sold (Trackers) | B4: =Inputs!C7 -> 600 | C4: =Inputs!D7 -> 1500 | D4: =Inputs!E7 -> 4000 | E4: =Inputs!F7 -> 15000 | F4: =Inputs!G7 -> 50000
A5: Subscription Users | B5: =Inputs!C8 -> 720 | C5: =Inputs!D8 -> 1800 | D5: =Inputs!E8 -> 4800 | E5: =Inputs!F8 -> 18000 | F5: =Inputs!G8 -> 60000
A6: Months Billed | B6: =Inputs!C9 -> 10 | C6: =Inputs!D9 -> 10.5 | D6: =Inputs!E9 -> 11 | E6: =Inputs!F9 -> 11.5 | F6: =Inputs!G9 -> 11.5
A7: Tracker Price (€) | B7: =Inputs!C12 -> 199 | C7: =Inputs!D12 -> 199 | D7: =Inputs!E12 -> 199 | E7: =Inputs!F12 -> 199 | F7: =Inputs!G12 -> 199
A8: Tracker Cost (€) | B8: =BOM!B15 -> 181 | C8: =BOM!B15 * 0.98 -> 177.38 | D8: =BOM!B15 * 0.96 -> 173.76 | E8: =BOM!B15 * 0.94 -> 170.14 | F8: =BOM!B15 * 0.92 -> 166.52
A9: Sub Price /mo (€) | B9: =Inputs!C13 -> 20 | C9: =Inputs!D13 -> 20 | D9: =Inputs!E13 -> 20 | E9: =Inputs!F13 -> 20 | F9: =Inputs!G13 -> 20
A10: Sat Cost /mo (€) | B10: =Inputs!C15 -> 6 | C10: =Inputs!D15 -> 6 | D10: =Inputs!E15 -> 6 | E10: =Inputs!F15 -> 6 | F10: =Inputs!G15 -> 6
A11: Hardware Revenue (€) | B11: =B4*(B7-B8) -> 10800 | C11: =C4*(C7-C8) -> 32430 | D11: =D4*(D7-D8) -> 100960 | E11: =E4*(E7-E8) -> 432900 | F11: =F4*(F7-F8) -> 1624000
A12: Subscription Revenue (€) | B12: =B5*B6*(B9-B10) -> 100800 | C12: =C5*C6*(C9-C10) -> 264600 | D12: =D5*D6*(D9-D10) -> 739200 | E12: =E5*E6*(E9-E10) -> 2898000 | F12: =F5*F6*(F9-F10) -> 9660000
A13: Salaries (€) | B13: =Inputs!C18 -> 160000 | C13: =Inputs!D18 -> 168000 | D13: =Inputs!E18 -> 184000 | E13: =Inputs!F18 -> 216000 | F13: =Inputs!G18 -> 256000
A14: Overheads (€) | B14: =Inputs!C19 -> 30000 | C14: =Inputs!D19 -> 31500 | D14: =Inputs!E19 -> 34500 | E14: =Inputs!F19 -> 40500 | F14: =Inputs!G19 -> 48000
A15: Cloud Infra Fixed (€) | B15: =Inputs!C21 -> 6000 | C15: =Inputs!D21 -> 6300 | D15: =Inputs!E21 -> 6900 | E15: =Inputs!F21 -> 8100 | F15: =Inputs!G21 -> 9600
A16: Marketing (€) | B16: =Inputs!C20 -> 5000 | C16: =Inputs!D20 -> 5250 | D16: =Inputs!E20 -> 5750 | E16: =Inputs!F20 -> 6750 | F16: =Inputs!G20 -> 8000
A17: Other Expenses (€) | B17: =Inputs!C22 -> 4000 | C17: =Inputs!D22 -> 4200 | D17: =Inputs!E22 -> 4600 | E17: =Inputs!F22 -> 5400 | F17: =Inputs!G22 -> 6400
A18: Operating Expenses (€) | B18: =SUM(B13:B17) -> 205000 | C18: =SUM(C13:C17) -> 215250 | D18: =SUM(D13:D17) -> 235750 | E18: =SUM(E13:E17) -> 276750 | F18: =SUM(F13:F17) -> 328000
A19: EBIT (€) | B19: =B11+B12-B18 -> -93400 | C19: =C11+C12-C18 -> 81780 | D19: =D11+D12-D18 -> 604410 | E19: =E11+E12-E18 -> 3054150 | F19: =F11+F12-F18 -> 10956000
